telegram_media_downloader-0.2.1.dist-info/licenses/LICENSE
telegram_media_downloader_bot/__init__.py
telegram_media_downloader_bot/__main__.py
telegram_media_downloader_bot/bot.py
telegram_media_downloader-0.2.1.dist-info/METADATA
telegram_media_downloader-0.2.1.dist-info/WHEEL
telegram_media_downloader-0.2.1.dist-info/top_level.txt
telegram_media_downloader-0.2.1.dist-info/RECORD
