Metadata-Version: 2.4
Name: telegram-media-downloader
Version: 0.2.1
Summary: A Telegram bot that downloads YouTube Shorts and Instagram Reels using yt_dlp.
Author-email: Ben Carver <benrcarver@gmail.com>
License-Expression: MIT
Requires-Python: >=3.8
License-File: LICENSE
Requires-Dist: python-telegram-bot>=20.0
Requires-Dist: requests>=2.25.0
Requires-Dist: beautifulsoup4>=4.9.0
Requires-Dist: yt-dlp>=2024.1.1
Provides-Extra: dev
Requires-Dist: pytest; extra == "dev"
Requires-Dist: pytest-asyncio; extra == "dev"
Requires-Dist: coverage; extra == "dev"
Dynamic: license-file
